[
  {
    "name": "physical",
    "hasDrop": true,
    "topics": {
      "manchesterE": {
        "name": "Manchester Encoding",
        "link": "physical/manchesterE"
      },
      "DmanchesterE": {
        "name": "Diffrential Manchester Encoding",
        "link": "physical/DmanchesterE"
      }
    }
  },
  {
    "name": "data-link",
    "hasDrop": true,
    "topics": {
      "StopAndWait": {
        "name": "Stop and Wait",
        "link": "dataLink/stopAndWait"
      },
      "SlidingWindow": {
        "name": "Sliding Window",
        "link": "dataLink/slidingWindow"
      }
    }
  }
]
